commons/__init__.py
commons/async_util/__init__.py
commons/async_util/create_task.py
commons/async_util/maybe_coro.py
commons/caching/__init__.py
commons/caching/timed_cache.py
commons/conditional_sleep.py
commons/exception_util.py
commons/hibp.py
commons/timing.py
commons/value_to_bool.py
skelmis_commons-1.6.1.dist-info/LICENSE
skelmis_commons-1.6.1.dist-info/METADATA
skelmis_commons-1.6.1.dist-info/WHEEL
skelmis_commons-1.6.1.dist-info/RECORD
